MANIFEST.in
README.md
setup.py
cyflash/__init__.py
cyflash/__main__.py
cyflash/bootload.py
cyflash/cyacd (1).py
cyflash/cyacd.py
cyflash/cyacd_test.py
cyflash/protocol.py
cyflash.egg-info/PKG-INFO
cyflash.egg-info/SOURCES.txt
cyflash.egg-info/dependency_links.txt
cyflash.egg-info/entry_points.txt
cyflash.egg-info/requires.txt
cyflash.egg-info/top_level.txt