Metadata-Version: 1.0
Name: cyflash
Version: 1.04
Summary: Tool for flashing data to Cypress PSoC devices via bootloader.
Home-page: http://github.com/arachnidlabs/cyflash/
Author: Nick Johnson
Author-email: nick@arachnidlabs.com
License: UNKNOWN
Platform: UNKNOWN
